recc_cache/__init__.py
recc_cache/cache.py
recc_cache/redis/__init__.py
recc_cache/redis/redis_cache.py
recc_cache-2.1.0.dist-info/LICENSE
recc_cache-2.1.0.dist-info/METADATA
recc_cache-2.1.0.dist-info/WHEEL
recc_cache-2.1.0.dist-info/top_level.txt
recc_cache-2.1.0.dist-info/RECORD
